nomuchcode/__init__.py
nomuchcode/example.py
nomuchcode-1.3.5.dist-info/LICENSE
nomuchcode-1.3.5.dist-info/METADATA
nomuchcode-1.3.5.dist-info/WHEEL
nomuchcode-1.3.5.dist-info/top_level.txt
nomuchcode-1.3.5.dist-info/RECORD
