Metadata-Version: 2.1
Name: nomuchcode
Version: 1.3.5
Summary: Short your codes with these common-used 11 functions!
Home-page: UNKNOWN
Author: Aasheesh Agarwal
Author-email: code.with.aasheesh@gmail.com
License: UNKNOWN
Platform: UNKNOWN
Classifier: Programming Language :: Python :: 3
Classifier: License :: OSI Approved :: MIT License
Classifier: Operating System :: OS Independent
Requires-Python: >=3.0
License-File: LICENSE
